[
    {
        "text": "Jul 21/25 Ville de Laval logo\nVille de Laval\nShare\nShow more options\nIng\u00e9nieur.e - \u00e9tudes techniques \nLaval, QC \u00b7 Reposted 3 days ago \u00b7 42 people clicked apply\nPromoted by hirer \u00b7 Responses managed off LinkedIn\n\n\n Hybrid\nMatches your job preferences, workplace type is Hybrid.\n\n Full-time\nMatches your job preferences, job type is Full-time.\n\nApply\n\nSave\nSave Ing\u00e9nieur.e - \u00e9tudes techniques  at Ville de Laval\nYour profile was shared with the job poster. Undo shared profile with the job posterUndo",
        "action": "none",
        "file_path": "",
        "datetime": "2025-07-21"
    },
    {
        "text": "On July 22/25 Job details\nJob title: Ingenieur Civil senior\nCompany: A&A Consultants\n\u00c0 propos de l'entreprise\nNotre client est une firme sp\u00e9cialis\u00e9e dans le domaine de l\u2019environnement, engag\u00e9e dans la protection des \u00e9cosyst\u00e8mes et de la sant\u00e9 publique. Dans le cadre de son d\u00e9veloppement, nous recherchons un ing\u00e9nieur civil sp\u00e9cialis\u00e9 en r\u00e9habilitation de sites contamin\u00e9s, qui jouera un r\u00f4le cl\u00e9 dans la conception et la mise en \u0153uvre de solutions innovantes pour la d\u00e9pollution des sols et des eaux souterraines.",
        "action": "none",
        "file_path": "",
        "datetime": "2025-07-22"
    },
    {
        "text": "Jul 29/25 pour le poste de Ing\u00e9nieur(e) Civil \u2013 Secteur minier et industriel au sein de AECOM",
        "action": "none",
        "file_path": "",
        "datetime": "2025-07-28"
    }
]